mlcube_k8s/__init__.py
mlcube_k8s/k8s_run.py
mlcube_k8s/main.py
mlcube_k8s/tests/__init__.py
mlcube_k8s/tests/test_get_runner_class.py
mlcube_k8s/tests/test_data/test_cube/mlcube.yaml
mlcube_k8s/tests/test_data/test_cube/platforms/docker.yaml
mlcube_k8s/tests/test_data/test_cube/run/kubernetes.yaml
mlcube_k8s-0.0.9.dist-info/METADATA
mlcube_k8s-0.0.9.dist-info/WHEEL
mlcube_k8s-0.0.9.dist-info/entry_points.txt
mlcube_k8s-0.0.9.dist-info/top_level.txt
mlcube_k8s-0.0.9.dist-info/RECORD
