Metadata-Version: 2.1
Name: mlcube-k8s
Version: 0.0.9
License: Apache 2.0
Requires-Python: >=3.6
Requires-Dist: mlcube (==0.0.9)
Requires-Dist: kubernetes (==12.0.0)
